sapimclient/__init__.py
sapimclient/__main__.py
sapimclient/client.py
sapimclient/const.py
sapimclient/deploy.py
sapimclient/exceptions.py
sapimclient/export.py
sapimclient/helpers.py
sapimclient/py.typed
sapimclient/model/__init__.py
sapimclient/model/base.py
sapimclient/model/data_type.py
sapimclient/model/pipeline.py
sapimclient/model/resource.py
sapimclient/model/rule_element.py
sapimclient/model/rule_element_owner.py
sapimclient-3.1.0.dist-info/LICENSE
sapimclient-3.1.0.dist-info/METADATA
sapimclient-3.1.0.dist-info/WHEEL
sapimclient-3.1.0.dist-info/entry_points.txt
sapimclient-3.1.0.dist-info/top_level.txt
sapimclient-3.1.0.dist-info/RECORD
