Metadata-Version: 2.1
Name: sapimclient
Version: 3.1.0
Author-email: Niels Perfors <niels.perfors1987@gmail.com>
License: MIT
Project-URL: Homepage, https://github.com/niro1987/sapimclient
Project-URL: Repository, https://github.com/niro1987/sapimclient.git
Project-URL: Issues, https://github.com/niro1987/sapimclient/issues
Keywords: SAP,Incentive Management
Classifier: Intended Audience :: Developers
Classifier: License :: OSI Approved :: MIT License
Classifier: Programming Language :: Python :: 3.11
Requires-Python: >=3.11
License-File: LICENSE
Requires-Dist: aiohttp >=3.0.0
Requires-Dist: pydantic >=2.6.0
Provides-Extra: cli
Requires-Dist: click >=8.1.7 ; extra == 'cli'
Requires-Dist: pandas >=2.2.2 ; extra == 'cli'
